durabletask/azurefunctions/__init__.py
durabletask/azurefunctions/client.py
durabletask/azurefunctions/constants.py
durabletask/azurefunctions/worker.py
durabletask/azurefunctions/decorators/__init__.py
durabletask/azurefunctions/decorators/durable_app.py
durabletask/azurefunctions/decorators/metadata.py
durabletask/azurefunctions/http/__init__.py
durabletask/azurefunctions/http/http_management_payload.py
durabletask/azurefunctions/internal/__init__.py
durabletask/azurefunctions/internal/azurefunctions_grpc_interceptor.py
durabletask/azurefunctions/internal/azurefunctions_null_stub.py
durabletask_azurefunctions-0.0.0.dev5.dist-info/METADATA
durabletask_azurefunctions-0.0.0.dev5.dist-info/WHEEL
durabletask_azurefunctions-0.0.0.dev5.dist-info/top_level.txt
durabletask_azurefunctions-0.0.0.dev5.dist-info/RECORD
